.gitignore
setup.py
ucasort/__init__.py
ucasort/allkeys-5.1.txt
ucasort/allkeys-5.2-silpa.txt
ucasort/allkeys-5.2.txt
ucasort/allkeys-6.0.0.txt
ucasort/allkeys-silpa-6.0.0.txt
ucasort/core.py
ucasort.egg-info/PKG-INFO
ucasort.egg-info/SOURCES.txt
ucasort.egg-info/dependency_links.txt
ucasort.egg-info/not-zip-safe
ucasort.egg-info/requires.txt
ucasort.egg-info/top_level.txt
ucasort/templates/ucasort.html