Metadata-Version: 1.0
Name: ucasort
Version: 0.1.1
Summary: Sort words basded on linguistics
Home-page: http://silpa.org.in/sort
Author: Santhosh Thottingal
Author-email: santhosh.thottingal@gmail.com
License: LGPL-3.0
Platform: UNKNOWN
